YuehuiMiji/README.md
YuehuiMiji/__init__.py
YuehuiMiji/__main__.py
YuehuiMiji/file.epub
YuehuiMiji/index.html
YuehuiMiji/css/__init__.py
YuehuiMiji/css/annotations.css
YuehuiMiji/css/main.css
YuehuiMiji/css/normalize.css
YuehuiMiji/css/popup.css
YuehuiMiji/font/__init__.py
YuehuiMiji/font/fontello.eot
YuehuiMiji/font/fontello.svg
YuehuiMiji/font/fontello.ttf
YuehuiMiji/font/fontello.woff
YuehuiMiji/img/__init__.py
YuehuiMiji/img/annotator-glyph-sprite.png
YuehuiMiji/img/annotator-icon-sprite.png
YuehuiMiji/img/apple-touch-icon.png
YuehuiMiji/img/cancelfullscreen.png
YuehuiMiji/img/close.png
YuehuiMiji/img/fullscreen.png
YuehuiMiji/img/loader.gif
YuehuiMiji/img/menu-icon.png
YuehuiMiji/img/save.png
YuehuiMiji/img/saved.png
YuehuiMiji/img/settings-s.png
YuehuiMiji/img/settings.png
YuehuiMiji/img/star.png
YuehuiMiji/js/__init__.py
YuehuiMiji/js/epub.js
YuehuiMiji/js/epub.min.js
YuehuiMiji/js/epub.min.map
YuehuiMiji/js/hooks.min.js
YuehuiMiji/js/hooks.min.map
YuehuiMiji/js/reader.js
YuehuiMiji/js/reader.js.map
YuehuiMiji/js/reader.min.js
YuehuiMiji/js/reader.min.map
YuehuiMiji/js/hooks/__init__.py
YuehuiMiji/js/hooks/extensions/__init__.py
YuehuiMiji/js/hooks/extensions/highlight.js
YuehuiMiji/js/libs/__init__.py
YuehuiMiji/js/libs/jquery.min.js
YuehuiMiji/js/libs/localforage.min.js
YuehuiMiji/js/libs/screenfull.js
YuehuiMiji/js/libs/screenfull.min.js
YuehuiMiji/js/libs/zip.min.js
YuehuiMiji/js/plugins/__init__.py
YuehuiMiji/js/plugins/hypothesis.js
YuehuiMiji/js/plugins/search.js
yuehui_miji-2022.10.11.0.dist-info/METADATA
yuehui_miji-2022.10.11.0.dist-info/WHEEL
yuehui_miji-2022.10.11.0.dist-info/entry_points.txt
yuehui_miji-2022.10.11.0.dist-info/top_level.txt
yuehui_miji-2022.10.11.0.dist-info/RECORD
